<?xml version="1.0" encoding="UTF-8"?>
<resources>   
    <string name="PLG_RESTORE_DB_CHOOSE_BACKUPFILE">Wählen Sie eine Backupdatei aus:</string> 
    <string name="PLG_RESTORE_DB_CHOOSE_BACKUPFILE_DESC">Hier wird die Backupdatei für die Wiederherstellung ausgewählt.\n\nACHTUNG: Das Plugin prüft nicht, ob die Version der Backup-Datei zur installierten Admidio-Version passt. Die Wiederherstellung einer nicht passenden Version kann zum Absturz von Admidio führen.</string> 
    <string name="PLG_RESTORE_DB_DESC">Dieses Plugin stellt die Admidio-Datenbank wieder her.</string>
    <string name="PLG_RESTORE_DB_LOGOUT">Logout und zurück zur Homepage</string> 
    <string name="PLG_RESTORE_DB_LOGOUT_DESC">Um alle Daten wieder sauber einzulesen, werden Sie beim Klick auf den Button von der aktuellen Sitzung abgemeldet.</string>   
    <string name="PLG_RESTORE_DB_MENU_URL_ERROR">Die Authorisierungsprüfung des Plugins ist fehlgeschlagen. Es konnte kein Menüpunkt mit dieser URL eindeutig identifiziert werden.\n\n=> #VAR1_BOLD#</string>
    <string name="PLG_RESTORE_DB_NO_BACKUPFILE">Es sind keine Backupdateien vorhanden.</string>    
    <string name="PLG_RESTORE_DB_PLUGIN_NAME">RESTORE_DB</string>
    <string name="PLG_RESTORE_DB_RESTORE">Wiederherstellen</string>
    <string name="PLG_RESTORE_DB_RESTORE_ERROR">Der Wiederherstellungsprozes wurde mit folgenden Fehlern beendet:\n\n</string> 
    <string name="PLG_RESTORE_DB_RESTORE_OK">Die Admidio-Datenbank ist wiederhergestellt.</string>
    <string name="PLG_RESTORE_DB_RESTORE_PROCESS">Der Wiederherstellungsprozess läuft.\n\nACHTUNG: Dieser Vorgang darf nicht abgebrochen werden.</string> 
</resources>